{"song":{"speed":1.8,"validScore":true,"player1":"bf","player2":"dad","notes":[{"lengthInSteps":16,"sectionNotes":[],"mustHitSection":false},{"lengthInSteps":16,"sectionNotes":[],"mustHitSection":true},{"lengthInSteps":16,"sectionNotes":[],"mustHitSection":false},{"lengthInSteps":16,"sectionNotes":[],"mustHitSection":true},{"lengthInSteps":16,"sectionNotes":[],"mustHitSection":false},{"lengthInSteps":16,"sectionNotes":[],"mustHitSection":true},{"lengthInSteps":16,"sectionNotes":[],"mustHitSection":false},{"lengthInSteps":16,"sectionNotes":[],"mustHitSection":true},{"lengthInSteps":16,"sectionNotes":[],"mustHitSection":false},{"lengthInSteps":16,"sectionNotes":[],"mustHitSection":true},{"lengthInSteps":16,"sectionNotes":[],"mustHitSection":false},{"lengthInSteps":16,"sectionNotes":[],"mustHitSection":true},{"lengthInSteps":16,"sectionNotes":[],"mustHitSection":false},{"lengthInSteps":16,"sectionNotes":[],"mustHitSection":false},{"lengthInSteps":16,"sectionNotes":[],"mustHitSection":true},{"lengthInSteps":16,"sectionNotes":[],"mustHitSection":true},{"lengthInSteps":16,"sectionNotes":[],"mustHitSection":false},{"lengthInSteps":16,"sectionNotes":[],"mustHitSection":false},{"lengthInSteps":16,"sectionNotes":[],"mustHitSection":true},{"lengthInSteps":16,"sectionNotes":[],"mustHitSection":true},{"lengthInSteps":16,"sectionNotes":[],"mustHitSection":false},{"lengthInSteps":16,"sectionNotes":[],"mustHitSection":true},{"lengthInSteps":16,"sectionNotes":[],"mustHitSection":false},{"lengthInSteps":16,"sectionNotes":[],"mustHitSection":true},{"lengthInSteps":16,"sectionNotes":[],"mustHitSection":false},{"lengthInSteps":16,"sectionNotes":[],"mustHitSection":true},{"lengthInSteps":16,"sectionNotes":[],"mustHitSection":false},{"lengthInSteps":16,"sectionNotes":[],"mustHitSection":true},{"lengthInSteps":16,"sectionNotes":[],"mustHitSection":false},{"lengthInSteps":16,"sectionNotes":[],"mustHitSection":false},{"lengthInSteps":16,"sectionNotes":[],"mustHitSection":true},{"lengthInSteps":16,"sectionNotes":[],"mustHitSection":true},{"lengthInSteps":16,"sectionNotes":[],"mustHitSection":false},{"lengthInSteps":16,"sectionNotes":[],"mustHitSection":false},{"lengthInSteps":16,"sectionNotes":[],"mustHitSection":true},{"lengthInSteps":16,"sectionNotes":[],"mustHitSection":true},{"lengthInSteps":16,"sectionNotes":[],"mustHitSection":true},{"lengthInSteps":16,"sectionNotes":[],"mustHitSection":true},{"lengthInSteps":16,"sectionNotes":[],"mustHitSection":true},{"lengthInSteps":16,"sectionNotes":[],"mustHitSection":true},{"lengthInSteps":16,"sectionNotes":[],"mustHitSection":true},{"lengthInSteps":16,"sectionNotes":[],"mustHitSection":true},{"altAnim":false,"typeOfSection":0,"lengthInSteps":16,"sectionNotes":[],"bpm":120,"mustHitSection":true,"changeBPM":false},{"altAnim":false,"typeOfSection":0,"lengthInSteps":16,"sectionNotes":[],"bpm":120,"mustHitSection":true,"changeBPM":false},{"altAnim":false,"typeOfSection":0,"lengthInSteps":16,"sectionNotes":[],"bpm":120,"mustHitSection":true,"changeBPM":false},{"altAnim":false,"typeOfSection":0,"lengthInSteps":16,"sectionNotes":[],"bpm":120,"mustHitSection":true,"changeBPM":false},{"altAnim":false,"typeOfSection":0,"lengthInSteps":16,"sectionNotes":[],"bpm":120,"mustHitSection":true,"changeBPM":false},{"altAnim":false,"typeOfSection":0,"lengthInSteps":16,"sectionNotes":[],"bpm":120,"mustHitSection":true,"changeBPM":false},{"altAnim":false,"typeOfSection":0,"lengthInSteps":16,"sectionNotes":[],"bpm":120,"mustHitSection":true,"changeBPM":false},{"altAnim":false,"typeOfSection":0,"lengthInSteps":16,"sectionNotes":[],"bpm":120,"mustHitSection":true,"changeBPM":false},{"altAnim":false,"typeOfSection":0,"lengthInSteps":16,"sectionNotes":[],"bpm":120,"mustHitSection":true,"changeBPM":false},{"altAnim":false,"typeOfSection":0,"lengthInSteps":16,"sectionNotes":[],"bpm":120,"mustHitSection":true,"changeBPM":false},{"altAnim":false,"bpm":120,"changeBPM":false,"lengthInSteps":16,"mustHitSection":true,"sectionNotes":[],"typeOfSection":0}],"bpm":120,"vocalVolume":0.8,"song":"Mesh","needsVoices":false}}